{
  "source": "sofascore",
  "date": "2026-07-21",
  "collectionState": "open",
  "firstScrapedAtUtc": "2026-07-21T20:23:18.152Z",
  "lastScrapedAtUtc": "2026-07-21T20:25:44.110Z",
  "frozenAtUtc": null,
  "fixtureCount": 23,
  "fixtures": [
    {
      "source": "sofascore",
      "sourceEventId": "15373033",
      "matchDate": "2026-07-21",
      "kickoffAtUtc": "2026-07-21T10:30:00.000Z",
      "competitionName": "K League 1",
      "countryName": "South Korea",
      "homeTeamId": "7649",
      "homeTeamName": "Jeju",
      "homeTeamLogoUrl": "https://img.sofascore.com/api/v1/team/7649/image/small",
      "awayTeamId": "34220",
      "awayTeamName": "Gangwon",
      "awayTeamLogoUrl": "https://img.sofascore.com/api/v1/team/34220/image/small",
      "status": "finished",
      "resultLabel": "FT",
      "homeScore": 1,
      "awayScore": 1,
      "matchUrl": "https://www.sofascore.com/football/match/gangwon-fc-jeju-sk/ZcdsvJn#id:15373033",
      "firstSeenAtUtc": "2026-07-21T20:23:18.152Z",
      "lastSeenAtUtc": "2026-07-21T20:25:44.110Z",
      "lastChangedAtUtc": "2026-07-21T20:24:26.579Z"
    },
    {
      "source": "sofascore",
      "sourceEventId": "15373034",
      "matchDate": "2026-07-21",
      "kickoffAtUtc": "2026-07-21T10:30:00.000Z",
      "competitionName": "K League 1",
      "countryName": "South Korea",
      "homeTeamId": "6908",
      "homeTeamName": "Jeonbuk",
      "homeTeamLogoUrl": "https://img.sofascore.com/api/v1/team/6908/image/small",
      "awayTeamId": "7645",
      "awayTeamName": "Daejeon Hana",
      "awayTeamLogoUrl": "https://img.sofascore.com/api/v1/team/7645/image/small",
      "status": "finished",
      "resultLabel": "FT",
      "homeScore": 0,
      "awayScore": 0,
      "matchUrl": "https://www.sofascore.com/football/match/daejeon-hana-citizen-jeonbuk-hyundai-motors/iNcsVcd#id:15373034",
      "firstSeenAtUtc": "2026-07-21T20:23:18.152Z",
      "lastSeenAtUtc": "2026-07-21T20:25:44.110Z",
      "lastChangedAtUtc": "2026-07-21T20:24:26.579Z"
    },
    {
      "source": "sofascore",
      "sourceEventId": "15373035",
      "matchDate": "2026-07-21",
      "kickoffAtUtc": "2026-07-21T10:30:00.000Z",
      "competitionName": "K League 1",
      "countryName": "South Korea",
      "homeTeamId": "7653",
      "homeTeamName": "Ulsan",
      "homeTeamLogoUrl": "https://img.sofascore.com/api/v1/team/7653/image/small",
      "awayTeamId": "7648",
      "awayTeamName": "Incheon Utd",
      "awayTeamLogoUrl": "https://img.sofascore.com/api/v1/team/7648/image/small",
      "status": "finished",
      "resultLabel": "FT",
      "homeScore": 1,
      "awayScore": 2,
      "matchUrl": "https://www.sofascore.com/football/match/ulsan-hd-incheon-united/Ycdsddd#id:15373035",
      "firstSeenAtUtc": "2026-07-21T20:23:18.152Z",
      "lastSeenAtUtc": "2026-07-21T20:25:44.110Z",
      "lastChangedAtUtc": "2026-07-21T20:24:26.579Z"
    },
    {
      "source": "sofascore",
      "sourceEventId": "16350227",
      "matchDate": "2026-07-21",
      "kickoffAtUtc": "2026-07-21T16:00:00.000Z",
      "competitionName": "UEFA Champions League, Qualification",
      "countryName": "Europe",
      "homeTeamId": "262229",
      "homeTeamName": "Ararat-Armenia",
      "homeTeamLogoUrl": "https://img.sofascore.com/api/v1/team/262229/image/small",
      "awayTeamId": "3177",
      "awayTeamName": "Shamrock Rovers",
      "awayTeamLogoUrl": "https://img.sofascore.com/api/v1/team/3177/image/small",
      "status": "finished",
      "resultLabel": "FT",
      "homeScore": 2,
      "awayScore": 0,
      "matchUrl": "https://www.sofascore.com/football/match/fc-ararat-armenia-shamrock-rovers/CnbsEUec#id:16350227",
      "firstSeenAtUtc": "2026-07-21T20:23:18.152Z",
      "lastSeenAtUtc": "2026-07-21T20:25:44.110Z",
      "lastChangedAtUtc": "2026-07-21T20:24:26.579Z"
    },
    {
      "source": "sofascore",
      "sourceEventId": "16350221",
      "matchDate": "2026-07-21",
      "kickoffAtUtc": "2026-07-21T16:00:00.000Z",
      "competitionName": "UEFA Champions League, Qualification",
      "countryName": "Europe",
      "homeTeamId": "116312",
      "homeTeamName": "Iberia",
      "homeTeamLogoUrl": "https://img.sofascore.com/api/v1/team/116312/image/small",
      "awayTeamId": "2404",
      "awayTeamName": "Slovan",
      "awayTeamLogoUrl": "https://img.sofascore.com/api/v1/team/2404/image/small",
      "status": "finished",
      "resultLabel": "FT",
      "homeScore": 0,
      "awayScore": 2,
      "matchUrl": "https://www.sofascore.com/football/match/fc-iberia-1999-sk-slovan-bratislava/eYsmBW#id:16350221",
      "firstSeenAtUtc": "2026-07-21T20:23:18.152Z",
      "lastSeenAtUtc": "2026-07-21T20:25:44.110Z",
      "lastChangedAtUtc": "2026-07-21T20:24:26.579Z"
    },
    {
      "source": "sofascore",
      "sourceEventId": "16350228",
      "matchDate": "2026-07-21",
      "kickoffAtUtc": "2026-07-21T16:00:00.000Z",
      "competitionName": "UEFA Champions League, Qualification",
      "countryName": "Europe",
      "homeTeamId": "1783",
      "homeTeamName": "Mjällby",
      "homeTeamLogoUrl": "https://img.sofascore.com/api/v1/team/1783/image/small",
      "awayTeamId": "126304",
      "awayTeamName": "Lincoln RI",
      "awayTeamLogoUrl": "https://img.sofascore.com/api/v1/team/126304/image/small",
      "status": "finished",
      "resultLabel": "FT",
      "homeScore": 3,
      "awayScore": 0,
      "matchUrl": "https://www.sofascore.com/football/match/lincoln-red-imps-mjallby-aif/IKseBab#id:16350228",
      "firstSeenAtUtc": "2026-07-21T20:23:18.152Z",
      "lastSeenAtUtc": "2026-07-21T20:25:44.110Z",
      "lastChangedAtUtc": "2026-07-21T20:24:26.579Z"
    },
    {
      "source": "sofascore",
      "sourceEventId": "16526434",
      "matchDate": "2026-07-21",
      "kickoffAtUtc": "2026-07-21T16:00:00.000Z",
      "competitionName": "UEFA Champions League, Qualification",
      "countryName": "Europe",
      "homeTeamId": "267828",
      "homeTeamName": "Sabah",
      "homeTeamLogoUrl": "https://img.sofascore.com/api/v1/team/267828/image/small",
      "awayTeamId": "2244",
      "awayTeamName": "KuPS",
      "awayTeamLogoUrl": "https://img.sofascore.com/api/v1/team/2244/image/small",
      "status": "finished",
      "resultLabel": "FT",
      "homeScore": 1,
      "awayScore": 0,
      "matchUrl": "https://www.sofascore.com/football/match/sabah-fk-kuopion-palloseura/UUsDghc#id:16526434",
      "firstSeenAtUtc": "2026-07-21T20:23:18.152Z",
      "lastSeenAtUtc": "2026-07-21T20:25:44.110Z",
      "lastChangedAtUtc": "2026-07-21T20:24:26.579Z"
    },
    {
      "source": "sofascore",
      "sourceEventId": "16350225",
      "matchDate": "2026-07-21",
      "kickoffAtUtc": "2026-07-21T17:00:00.000Z",
      "competitionName": "UEFA Champions League, Qualification",
      "countryName": "Europe",
      "homeTeamId": "1291",
      "homeTeamName": "AGF",
      "homeTeamLogoUrl": "https://img.sofascore.com/api/v1/team/1291/image/small",
      "awayTeamId": "3121",
      "awayTeamName": "Lech",
      "awayTeamLogoUrl": "https://img.sofascore.com/api/v1/team/3121/image/small",
      "status": "finished",
      "resultLabel": "FT",
      "homeScore": 1,
      "awayScore": 4,
      "matchUrl": "https://www.sofascore.com/football/match/lech-poznan-agf/QAswmb#id:16350225",
      "firstSeenAtUtc": "2026-07-21T20:23:18.152Z",
      "lastSeenAtUtc": "2026-07-21T20:25:44.110Z",
      "lastChangedAtUtc": "2026-07-21T20:24:26.579Z"
    },
    {
      "source": "sofascore",
      "sourceEventId": "16351121",
      "matchDate": "2026-07-21",
      "kickoffAtUtc": "2026-07-21T17:00:00.000Z",
      "competitionName": "UEFA Conference League, Qualification",
      "countryName": "Europe",
      "homeTeamId": "1761",
      "homeTeamName": "Göteborg",
      "homeTeamLogoUrl": "https://img.sofascore.com/api/v1/team/1761/image/small",
      "awayTeamId": "3342",
      "awayTeamName": "Levadia",
      "awayTeamLogoUrl": "https://img.sofascore.com/api/v1/team/3342/image/small",
      "status": "finished",
      "resultLabel": "FT",
      "homeScore": 1,
      "awayScore": 2,
      "matchUrl": "https://www.sofascore.com/football/match/fci-levadia-tallinn-ifk-goteborg/lKsRqb#id:16351121",
      "firstSeenAtUtc": "2026-07-21T20:23:18.152Z",
      "lastSeenAtUtc": "2026-07-21T20:25:44.110Z",
      "lastChangedAtUtc": "2026-07-21T20:24:26.579Z"
    },
    {
      "source": "sofascore",
      "sourceEventId": "16357200",
      "matchDate": "2026-07-21",
      "kickoffAtUtc": "2026-07-21T17:30:00.000Z",
      "competitionName": "UEFA Conference League, Qualification",
      "countryName": "Europe",
      "homeTeamId": "33584",
      "homeTeamName": "Floriana",
      "homeTeamLogoUrl": "https://img.sofascore.com/api/v1/team/33584/image/small",
      "awayTeamId": "229755",
      "awayTeamName": "Drita",
      "awayTeamLogoUrl": "https://img.sofascore.com/api/v1/team/229755/image/small",
      "status": "finished",
      "resultLabel": "FT",
      "homeScore": 1,
      "awayScore": 1,
      "matchUrl": "https://www.sofascore.com/football/match/fc-drita-floriana-fc/JwnsfVQb#id:16357200",
      "firstSeenAtUtc": "2026-07-21T20:23:18.152Z",
      "lastSeenAtUtc": "2026-07-21T20:25:44.110Z",
      "lastChangedAtUtc": "2026-07-21T20:24:26.579Z"
    },
    {
      "source": "sofascore",
      "sourceEventId": "16350222",
      "matchDate": "2026-07-21",
      "kickoffAtUtc": "2026-07-21T18:00:00.000Z",
      "competitionName": "UEFA Champions League, Qualification",
      "countryName": "Europe",
      "homeTeamId": "3052",
      "homeTeamName": "Fenerbahçe",
      "homeTeamLogoUrl": "https://img.sofascore.com/api/v1/team/3052/image/small",
      "awayTeamId": "3110",
      "awayTeamName": "Górnik",
      "awayTeamLogoUrl": "https://img.sofascore.com/api/v1/team/3110/image/small",
      "status": "finished",
      "resultLabel": "FT",
      "homeScore": 1,
      "awayScore": 0,
      "matchUrl": "https://www.sofascore.com/football/match/gornik-zabrze-fenerbahce/clbskmb#id:16350222",
      "firstSeenAtUtc": "2026-07-21T20:23:18.152Z",
      "lastSeenAtUtc": "2026-07-21T20:25:44.110Z",
      "lastChangedAtUtc": "2026-07-21T20:24:26.579Z"
    },
    {
      "source": "sofascore",
      "sourceEventId": "16350223",
      "matchDate": "2026-07-21",
      "kickoffAtUtc": "2026-07-21T18:00:00.000Z",
      "competitionName": "UEFA Champions League, Qualification",
      "countryName": "Europe",
      "homeTeamId": "2454",
      "homeTeamName": "Thun",
      "homeTeamLogoUrl": "https://img.sofascore.com/api/v1/team/2454/image/small",
      "awayTeamId": "2032",
      "awayTeamName": "Dinamo",
      "awayTeamLogoUrl": "https://img.sofascore.com/api/v1/team/2032/image/small",
      "status": "finished",
      "resultLabel": "FT",
      "homeScore": 1,
      "awayScore": 1,
      "matchUrl": "https://www.sofascore.com/football/match/fc-thun-gnk-dinamo-zagreb/HPseZ#id:16350223",
      "firstSeenAtUtc": "2026-07-21T20:23:18.152Z",
      "lastSeenAtUtc": "2026-07-21T20:25:44.110Z",
      "lastChangedAtUtc": "2026-07-21T20:24:26.579Z"
    },
    {
      "source": "sofascore",
      "sourceEventId": "16357195",
      "matchDate": "2026-07-21",
      "kickoffAtUtc": "2026-07-21T18:15:00.000Z",
      "competitionName": "UEFA Conference League, Qualification",
      "countryName": "Europe",
      "homeTeamId": "38989",
      "homeTeamName": "Bissen",
      "homeTeamLogoUrl": "https://img.sofascore.com/api/v1/team/38989/image/small",
      "awayTeamId": "1923",
      "awayTeamName": "Győr",
      "awayTeamLogoUrl": "https://img.sofascore.com/api/v1/team/1923/image/small",
      "status": "finished",
      "resultLabel": "FT",
      "homeScore": 2,
      "awayScore": 6,
      "matchUrl": "https://www.sofascore.com/football/match/atert-bissen-eto-fc-gyor/yNsOEp#id:16357195",
      "firstSeenAtUtc": "2026-07-21T20:23:18.152Z",
      "lastSeenAtUtc": "2026-07-21T20:25:44.110Z",
      "lastChangedAtUtc": "2026-07-21T20:24:26.579Z"
    },
    {
      "source": "sofascore",
      "sourceEventId": "16350220",
      "matchDate": "2026-07-21",
      "kickoffAtUtc": "2026-07-21T18:30:00.000Z",
      "competitionName": "UEFA Champions League, Qualification",
      "countryName": "Europe",
      "homeTeamId": "2051",
      "homeTeamName": "Sturm",
      "homeTeamLogoUrl": "https://img.sofascore.com/api/v1/team/2051/image/small",
      "awayTeamId": "2353",
      "awayTeamName": "Hearts",
      "awayTeamLogoUrl": "https://img.sofascore.com/api/v1/team/2353/image/small",
      "status": "finished",
      "resultLabel": "FT",
      "homeScore": 4,
      "awayScore": 0,
      "matchUrl": "https://www.sofascore.com/football/match/heart-of-midlothian-sk-sturm-graz/bQsdX#id:16350220",
      "firstSeenAtUtc": "2026-07-21T20:23:18.152Z",
      "lastSeenAtUtc": "2026-07-21T20:25:44.110Z",
      "lastChangedAtUtc": "2026-07-21T20:25:44.110Z"
    },
    {
      "source": "sofascore",
      "sourceEventId": "16350226",
      "matchDate": "2026-07-21",
      "kickoffAtUtc": "2026-07-21T18:45:00.000Z",
      "competitionName": "UEFA Champions League, Qualification",
      "countryName": "Europe",
      "homeTeamId": "5194",
      "homeTeamName": "Klaksvík",
      "homeTeamLogoUrl": "https://img.sofascore.com/api/v1/team/5194/image/small",
      "awayTeamId": "80741",
      "awayTeamName": "Kauno Žalgiris",
      "awayTeamLogoUrl": "https://img.sofascore.com/api/v1/team/80741/image/small",
      "status": "live",
      "resultLabel": "85'",
      "homeScore": 0,
      "awayScore": 0,
      "matchUrl": "https://www.sofascore.com/football/match/fk-kauno-zalgiris-klaksvikar-itrottarfelag/UdcsQoH#id:16350226",
      "firstSeenAtUtc": "2026-07-21T20:23:18.152Z",
      "lastSeenAtUtc": "2026-07-21T20:25:44.110Z",
      "lastChangedAtUtc": "2026-07-21T20:25:44.110Z"
    },
    {
      "source": "sofascore",
      "sourceEventId": "16350234",
      "matchDate": "2026-07-21",
      "kickoffAtUtc": "2026-07-21T19:00:00.000Z",
      "competitionName": "UEFA Champions League, Qualification",
      "countryName": "Europe",
      "homeTeamId": "5184",
      "homeTeamName": "Larne FC",
      "homeTeamLogoUrl": "https://img.sofascore.com/api/v1/team/5184/image/small",
      "awayTeamId": "5149",
      "awayTeamName": "Crvena zvezda",
      "awayTeamLogoUrl": "https://img.sofascore.com/api/v1/team/5149/image/small",
      "status": "live",
      "resultLabel": "67'",
      "homeScore": 0,
      "awayScore": 2,
      "matchUrl": "https://www.sofascore.com/football/match/larne-fc-fk-crvena-zvezda/ZccsJdc#id:16350234",
      "firstSeenAtUtc": "2026-07-21T20:23:18.152Z",
      "lastSeenAtUtc": "2026-07-21T20:25:44.110Z",
      "lastChangedAtUtc": "2026-07-21T20:25:44.110Z"
    },
    {
      "source": "sofascore",
      "sourceEventId": "16350232",
      "matchDate": "2026-07-21",
      "kickoffAtUtc": "2026-07-21T19:00:00.000Z",
      "competitionName": "UEFA Champions League, Qualification",
      "countryName": "Europe",
      "homeTeamId": "1908",
      "homeTeamName": "Víkingur",
      "homeTeamLogoUrl": "https://img.sofascore.com/api/v1/team/1908/image/small",
      "awayTeamId": "5202",
      "awayTeamName": "H. Be'er Sheva",
      "awayTeamLogoUrl": "https://img.sofascore.com/api/v1/team/5202/image/small",
      "status": "live",
      "resultLabel": "69'",
      "homeScore": 1,
      "awayScore": 1,
      "matchUrl": "https://www.sofascore.com/football/match/hapoel-beer-sheva-vikingur-reykjavik/iNscec#id:16350232",
      "firstSeenAtUtc": "2026-07-21T20:23:18.152Z",
      "lastSeenAtUtc": "2026-07-21T20:25:44.110Z",
      "lastChangedAtUtc": "2026-07-21T20:25:44.110Z"
    },
    {
      "source": "sofascore",
      "sourceEventId": "15502618",
      "matchDate": "2026-07-21",
      "kickoffAtUtc": "2026-07-21T21:30:00.000Z",
      "competitionName": "LigaPro Serie A, Primera Etapa",
      "countryName": "Ecuador",
      "homeTeamId": "394127",
      "homeTeamName": "Libertad",
      "homeTeamLogoUrl": "https://img.sofascore.com/api/v1/team/394127/image/small",
      "awayTeamId": "213638",
      "awayTeamName": "Delfín",
      "awayTeamLogoUrl": "https://img.sofascore.com/api/v1/team/213638/image/small",
      "status": "upcoming",
      "resultLabel": "-",
      "homeScore": null,
      "awayScore": null,
      "matchUrl": "https://www.sofascore.com/football/match/libertad-delfin/NxKbsCHhd#id:15502618",
      "firstSeenAtUtc": "2026-07-21T20:23:18.152Z",
      "lastSeenAtUtc": "2026-07-21T20:25:44.110Z",
      "lastChangedAtUtc": "2026-07-21T20:25:44.110Z"
    },
    {
      "source": "sofascore",
      "sourceEventId": "16251104",
      "matchDate": "2026-07-21",
      "kickoffAtUtc": "2026-07-21T22:00:00.000Z",
      "competitionName": "CONMEBOL Sudamericana, Knockout stage",
      "countryName": "South America",
      "homeTeamId": "3230",
      "homeTeamName": "Nacional",
      "homeTeamLogoUrl": "https://img.sofascore.com/api/v1/team/3230/image/small",
      "awayTeamId": "7628",
      "awayTeamName": "Tigre",
      "awayTeamLogoUrl": "https://img.sofascore.com/api/v1/team/7628/image/small",
      "status": "upcoming",
      "resultLabel": "-",
      "homeScore": null,
      "awayScore": null,
      "matchUrl": "https://www.sofascore.com/football/match/tigre-nacional/FobsDcd#id:16251104",
      "firstSeenAtUtc": "2026-07-21T20:23:18.152Z",
      "lastSeenAtUtc": "2026-07-21T20:25:44.110Z",
      "lastChangedAtUtc": "2026-07-21T20:25:44.110Z"
    },
    {
      "source": "sofascore",
      "sourceEventId": "15237980",
      "matchDate": "2026-07-21",
      "kickoffAtUtc": "2026-07-21T22:30:00.000Z",
      "competitionName": "Brasileirão Betano",
      "countryName": "Brazil",
      "homeTeamId": "1977",
      "homeTeamName": "Atlético-MG",
      "homeTeamLogoUrl": "https://img.sofascore.com/api/v1/team/1977/image/small",
      "awayTeamId": "1955",
      "awayTeamName": "Bahia",
      "awayTeamLogoUrl": "https://img.sofascore.com/api/v1/team/1955/image/small",
      "status": "upcoming",
      "resultLabel": "-",
      "homeScore": null,
      "awayScore": null,
      "matchUrl": "https://www.sofascore.com/football/match/atletico-mineiro-bahia/fOsCO#id:15237980",
      "firstSeenAtUtc": "2026-07-21T20:23:18.152Z",
      "lastSeenAtUtc": "2026-07-21T20:25:44.110Z",
      "lastChangedAtUtc": "2026-07-21T20:25:44.110Z"
    },
    {
      "source": "sofascore",
      "sourceEventId": "15526194",
      "matchDate": "2026-07-21",
      "kickoffAtUtc": "2026-07-21T22:30:00.000Z",
      "competitionName": "Brasileirão Série B",
      "countryName": "Brazil",
      "homeTeamId": "7315",
      "homeTeamName": "Avaí",
      "homeTeamLogoUrl": "https://img.sofascore.com/api/v1/team/7315/image/small",
      "awayTeamId": "1973",
      "awayTeamName": "América-MG",
      "awayTeamLogoUrl": "https://img.sofascore.com/api/v1/team/1973/image/small",
      "status": "upcoming",
      "resultLabel": "-",
      "homeScore": null,
      "awayScore": null,
      "matchUrl": "https://www.sofascore.com/football/match/avai-america-mineiro/yOspWc#id:15526194",
      "firstSeenAtUtc": "2026-07-21T20:23:18.152Z",
      "lastSeenAtUtc": "2026-07-21T20:25:44.110Z",
      "lastChangedAtUtc": "2026-07-21T20:25:44.110Z"
    },
    {
      "source": "sofascore",
      "sourceEventId": "15526189",
      "matchDate": "2026-07-21",
      "kickoffAtUtc": "2026-07-21T22:30:00.000Z",
      "competitionName": "Brasileirão Série B",
      "countryName": "Brazil",
      "homeTeamId": "135514",
      "homeTeamName": "Novorizontino",
      "homeTeamLogoUrl": "https://img.sofascore.com/api/v1/team/135514/image/small",
      "awayTeamId": "1984",
      "awayTeamName": "Criciúma",
      "awayTeamLogoUrl": "https://img.sofascore.com/api/v1/team/1984/image/small",
      "status": "upcoming",
      "resultLabel": "-",
      "homeScore": null,
      "awayScore": null,
      "matchUrl": "https://www.sofascore.com/football/match/gremio-novorizontino-criciuma/JOsokeb#id:15526189",
      "firstSeenAtUtc": "2026-07-21T20:23:18.152Z",
      "lastSeenAtUtc": "2026-07-21T20:25:44.110Z",
      "lastChangedAtUtc": "2026-07-21T20:25:44.110Z"
    },
    {
      "source": "sofascore",
      "sourceEventId": "16389605",
      "matchDate": "2026-07-21",
      "kickoffAtUtc": "2026-07-21T23:00:00.000Z",
      "competitionName": "División Profesional",
      "countryName": "Bolivia",
      "homeTeamId": "372975",
      "homeTeamName": "Independiente Petrolero",
      "homeTeamLogoUrl": "https://img.sofascore.com/api/v1/team/372975/image/small",
      "awayTeamId": "7060",
      "awayTeamName": "Real Potosí",
      "awayTeamLogoUrl": "https://img.sofascore.com/api/v1/team/7060/image/small",
      "status": "upcoming",
      "resultLabel": "-",
      "homeScore": null,
      "awayScore": null,
      "matchUrl": "https://www.sofascore.com/football/match/club-independiente-petrolero-real-potosi/kQcsAjZc#id:16389605",
      "firstSeenAtUtc": "2026-07-21T20:23:18.152Z",
      "lastSeenAtUtc": "2026-07-21T20:25:44.110Z",
      "lastChangedAtUtc": "2026-07-21T20:25:44.110Z"
    }
  ],
  "metadata": {
    "browserTimezone": "UTC",
    "scraperVersion": 2
  }
}