{
  "source": "sofascore",
  "sourceEventId": "16384084",
  "matchUrl": "https://www.sofascore.com/football/match/fc-viktoria-plzen-fc-slovan-liberec/uUscPb#id:16384084",
  "status": "upcoming",
  "scrapedAtUtc": "2026-07-24T08:55:22.407Z",
  "fixtureLastSeenAtUtc": "2026-07-24T08:54:09.799Z",
  "fixtureLastChangedAtUtc": "2026-07-23T13:33:13.125Z",
  "overview": {
    "kickoffAtUtc": "2026-07-25T15:00:00.000Z",
    "competitionId": "172",
    "competitionName": "Czech First League",
    "competitionLogoUrl": "https://img.sofascore.com/api/v1/unique-tournament/172/image",
    "competitionStage": null,
    "countryName": "Czechia",
    "venueName": null,
    "venueCity": null,
    "venueCountry": null,
    "refereeName": null,
    "refereeCountry": null
  },
  "watch": {
    "hasPortugalChannels": true,
    "availableCountryCodes": [
      "DE",
      "FR",
      "PL",
      "PT"
    ],
    "note": "Canais disponíveis para Portugal."
  },
  "odds": {
    "providerId": 801,
    "marketName": "Full time",
    "home": "1.44",
    "draw": "3.97",
    "away": "5.15",
    "hasMoreOdds": true
  },
  "tieContext": {
    "tieFormat": null,
    "previousLeg": null,
    "nextLeg": null,
    "h2h": [
      {
        "sourceEventId": "16506097",
        "matchUrl": "https://www.sofascore.com/football/match/fc-viktoria-plzen-fc-slovan-liberec/uUscPb#id:16506097",
        "kickoffAtUtc": "2027-04-24T12:00:00.000Z",
        "competitionName": "Czech First League",
        "countryName": "Czech Republic",
        "roundName": null,
        "homeTeamId": "2219",
        "homeTeamName": "FC Slovan Liberec",
        "awayTeamId": "4502",
        "awayTeamName": "FC Viktoria Plzeň",
        "homeScore": null,
        "awayScore": null,
        "status": "upcoming",
        "resultLabel": "Not started",
        "previousLegEventId": null,
        "winnerCode": null
      },
      {
        "sourceEventId": "16073306",
        "matchUrl": "https://www.sofascore.com/football/match/fc-viktoria-plzen-fc-slovan-liberec/uUscPb#id:16073306",
        "kickoffAtUtc": "2026-05-09T14:00:00.000Z",
        "competitionName": "Czech First League, Championship",
        "countryName": "Czech Republic",
        "roundName": null,
        "homeTeamId": "4502",
        "homeTeamName": "FC Viktoria Plzeň",
        "awayTeamId": "2219",
        "awayTeamName": "FC Slovan Liberec",
        "homeScore": 2,
        "awayScore": 0,
        "status": "finished",
        "resultLabel": "FT",
        "previousLegEventId": null,
        "winnerCode": 1
      },
      {
        "sourceEventId": "14036561",
        "matchUrl": "https://www.sofascore.com/football/match/viktoria-plzen-fc-slovan-liberec/uUscPb#id:14036561",
        "kickoffAtUtc": "2026-02-08T17:30:00.000Z",
        "competitionName": "Czech First League",
        "countryName": "Czech Republic",
        "roundName": null,
        "homeTeamId": "4502",
        "homeTeamName": "FC Viktoria Plzeň",
        "awayTeamId": "2219",
        "awayTeamName": "FC Slovan Liberec",
        "homeScore": 3,
        "awayScore": 1,
        "status": "finished",
        "resultLabel": "FT",
        "previousLegEventId": null,
        "winnerCode": 1
      },
      {
        "sourceEventId": "14036381",
        "matchUrl": "https://www.sofascore.com/football/match/viktoria-plzen-fc-slovan-liberec/uUscPb#id:14036381",
        "kickoffAtUtc": "2025-08-31T13:00:00.000Z",
        "competitionName": "Czech First League",
        "countryName": "Czech Republic",
        "roundName": null,
        "homeTeamId": "2219",
        "homeTeamName": "FC Slovan Liberec",
        "awayTeamId": "4502",
        "awayTeamName": "FC Viktoria Plzeň",
        "homeScore": 1,
        "awayScore": 1,
        "status": "finished",
        "resultLabel": "FT",
        "previousLegEventId": null,
        "winnerCode": 3
      },
      {
        "sourceEventId": "12580743",
        "matchUrl": "https://www.sofascore.com/football/match/viktoria-plzen-fc-slovan-liberec/uUscPb#id:12580743",
        "kickoffAtUtc": "2025-02-08T18:00:00.000Z",
        "competitionName": "Czech First League",
        "countryName": "Czech Republic",
        "roundName": null,
        "homeTeamId": "4502",
        "homeTeamName": "FC Viktoria Plzeň",
        "awayTeamId": "2219",
        "awayTeamName": "FC Slovan Liberec",
        "homeScore": 3,
        "awayScore": 2,
        "status": "finished",
        "resultLabel": "FT",
        "previousLegEventId": null,
        "winnerCode": 1
      }
    ]
  },
  "recent": {
    "homeLast": [
      {
        "sourceEventId": "14572808",
        "matchUrl": "https://www.sofascore.com/football/match/viktoria-plzen-panathinaikos/YobscPb#id:14572808",
        "kickoffAtUtc": "2025-12-11T20:00:00.000Z",
        "competitionName": "UEFA Europa League",
        "countryName": "Europe",
        "roundName": null,
        "homeTeamId": "3248",
        "homeTeamName": "Panathinaikos FC",
        "awayTeamId": "4502",
        "awayTeamName": "FC Viktoria Plzeň",
        "homeScore": 0,
        "awayScore": 0,
        "status": "finished",
        "resultLabel": "FT",
        "previousLegEventId": null,
        "winnerCode": 3
      },
      {
        "sourceEventId": "14036533",
        "matchUrl": "https://www.sofascore.com/football/match/dukla-praha-viktoria-plzen/cPbsOed#id:14036533",
        "kickoffAtUtc": "2025-12-14T14:30:00.000Z",
        "competitionName": "Czech First League",
        "countryName": "Czech Republic",
        "roundName": null,
        "homeTeamId": "4502",
        "homeTeamName": "FC Viktoria Plzeň",
        "awayTeamId": "7739",
        "awayTeamName": "Dukla Praha",
        "homeScore": 2,
        "awayScore": 0,
        "status": "finished",
        "resultLabel": "FT",
        "previousLegEventId": null,
        "winnerCode": 1
      },
      {
        "sourceEventId": "15289416",
        "matchUrl": "https://www.sofascore.com/football/match/viktoria-plzen-fc-lugano/TYscPb#id:15289416",
        "kickoffAtUtc": "2026-01-09T09:30:00.000Z",
        "competitionName": "Club Friendly Games",
        "countryName": "World",
        "roundName": null,
        "homeTeamId": "2443",
        "homeTeamName": "FC Lugano",
        "awayTeamId": "4502",
        "awayTeamName": "FC Viktoria Plzeň",
        "homeScore": 2,
        "awayScore": 4,
        "status": "finished",
        "resultLabel": "FT",
        "previousLegEventId": null,
        "winnerCode": 2
      }
    ],
    "homeNext": [
      {
        "sourceEventId": "16456079",
        "matchUrl": "https://www.sofascore.com/football/match/fc-viktoria-plzen-fc-zbrojovka-brno/kUscPb#id:16456079",
        "kickoffAtUtc": "2026-08-01T18:00:00.000Z",
        "competitionName": "Czech First League",
        "countryName": "Czech Republic",
        "roundName": null,
        "homeTeamId": "4502",
        "homeTeamName": "FC Viktoria Plzeň",
        "awayTeamId": "2210",
        "awayTeamName": "FC Zbrojovka Brno",
        "homeScore": null,
        "awayScore": null,
        "status": "upcoming",
        "resultLabel": "Not started",
        "previousLegEventId": null,
        "winnerCode": null
      },
      {
        "sourceEventId": "16453919",
        "matchUrl": "https://www.sofascore.com/football/match/fc-viktoria-plzen-fk-teplice/iUscPb#id:16453919",
        "kickoffAtUtc": "2026-08-08T15:00:00.000Z",
        "competitionName": "Czech First League",
        "countryName": "Czech Republic",
        "roundName": null,
        "homeTeamId": "2208",
        "homeTeamName": "FK Teplice",
        "awayTeamId": "4502",
        "awayTeamName": "FC Viktoria Plzeň",
        "homeScore": null,
        "awayScore": null,
        "status": "upcoming",
        "resultLabel": "Not started",
        "previousLegEventId": null,
        "winnerCode": null
      }
    ],
    "awayLast": [],
    "awayNext": []
  }
}